{"type": "Feature", "id": 12524388, "geometry": {"type": "Point", "coordinates": [-84.599998, 13.95]}, "properties": {"woe:id": 12524388, "woe:parent_id": 152170, "woe:name": "San Pedro Airport", "woe:placetype": 14, "woe:placetype_name": "Airport", "woe:lang": "ENG", "iso:country": "NI", "meta:provider": ["geoplanet:7.3.1", "geoplanet:7.3.2", "geoplanet:7.4.0", "geoplanet:7.4.1", "geoplanet:7.5.1", "geoplanet:7.5.2", "geoplanet:7.6.0", "geoplanet:7.8.1", "geoplanet:7.9.0", "geoplanet:7.10.0", "geoplanet:8.0.0", "woeplanet:8.0.0"], "meta:indexed": "2020-08-20T20:19:22.302779", "woe:alias_ENG_V": ["BZA Airport", "BZA"], "meta:updated": "2020-10-14T11:29:09.040271", "woe:hierarchy": {"continent": 24865672, "country": 23424915, "town": 0, "planet": 1, "county": 26813422, "suburb": 0, "state": 20069833, "region": 0, "localadmin": 0}, "woe:timezone_id": 28350771, "woe:hash": "d47z6gs0thmr", "woe:centroid": [-84.599998, 13.95], "geom:latitude": 13.95, "geom:longitude": -84.599998, "geom:hash": "d47z6gs0thmr", "woe:latitude": 13.95, "geom:centroid": [-84.599998, 13.95], "woe:longitude": -84.599998, "woe:repo": "woeplanet-airport-ni", "geom:area": 0.0, "woe:scale": 19}}